README.rst
setup.py
pypi_check/__init__.py
pypi_check/pypi.py
pypi_check.egg-info/PKG-INFO
pypi_check.egg-info/SOURCES.txt
pypi_check.egg-info/dependency_links.txt
pypi_check.egg-info/entry_points.txt
pypi_check.egg-info/requires.txt
pypi_check.egg-info/top_level.txt