Metadata-Version: 1.1
Name: pypi-check
Version: 0.1.1
Summary: Check availability of PyPI package names
Home-page: https://github.com/harshasrinivas/pypi-check/
Author: Harsha Srinivas
Author-email: 95harsha95@gmail.com
License: UNKNOWN
Keywords: CLI,python
Platform: UNKNOWN
Classifier: Operating System :: POSIX
Classifier: Environment :: Console
Classifier: Programming Language :: Python
Classifier: Programming Language :: Python :: 2
Classifier: Programming Language :: Python :: 3
Classifier: Programming Language :: Python :: 3.2
Classifier: Programming Language :: Python :: 3.3
Classifier: Topic :: Utilities
Classifier: Topic :: Software Development :: Libraries :: Python Modules
